adafruit_lc709203f.py
adafruit_circuitpython_lc709203f-2.3.8.dist-info/licenses/LICENSE
adafruit_circuitpython_lc709203f-2.3.8.dist-info/METADATA
adafruit_circuitpython_lc709203f-2.3.8.dist-info/WHEEL
adafruit_circuitpython_lc709203f-2.3.8.dist-info/top_level.txt
adafruit_circuitpython_lc709203f-2.3.8.dist-info/RECORD
