Metadata-Version: 2.4
Name: adafruit-circuitpython-lc709203f
Version: 2.3.8
Summary: Library for I2C LC709203F battery status and fuel gauge
Author-email: Adafruit Industries <circuitpython@adafruit.com>
License: MIT
Project-URL: Homepage, https://github.com/adafruit/Adafruit_CircuitPython_LC709203F
Keywords: adafruit,blinka,circuitpython,micropython,lc709203f,battery,lipoly,status,fuel,gauge,i2c
Classifier: Intended Audience :: Developers
Classifier: Topic :: Software Development :: Libraries
Classifier: Topic :: Software Development :: Embedded Systems
Classifier: Topic :: System :: Hardware
Classifier: License :: OSI Approved :: MIT License
Classifier: Programming Language :: Python :: 3
License-File: LICENSE
Requires-Dist: Adafruit-Blinka
Requires-Dist: adafruit-circuitpython-register
Requires-Dist: adafruit-circuitpython-busdevice
Requires-Dist: adafruit-circuitpython-typing
Requires-Dist: typing-extensions~=4.0
Provides-Extra: optional
Dynamic: license-file
